{"explore_is_explore": {"left": 53, "top": 579, "right": 99, "bottom": 625, "width": 44, "height": 44}, "explore_is_evo_entrance": {"left": 56, "top": 572, "right": 99, "bottom": 621, "width": 41, "height": 47}, "explore_is_soul_entrance": {"left": 147, "top": 574, "right": 183, "bottom": 608, "width": 34, "height": 32}, "explore_is_realm_raid_entrance": {"left": 230, "top": 570, "right": 267, "bottom": 605, "width": 35, "height": 33}, "explore_is_totem_entrance": {"left": 315, "top": 570, "right": 351, "bottom": 608, "width": 34, "height": 36}, "explore_is_stories_entrance": {"left": 399, "top": 574, "right": 442, "bottom": 610, "width": 41, "height": 34}, "explore_is_delegate_entrance": {"left": 494, "top": 566, "right": 532, "bottom": 604, "width": 36, "height": 36}, "explore_is_secret_zone_entrance": {"left": 574, "top": 568, "right": 612, "bottom": 602, "width": 36, "height": 32}, "explore_is_area_boss_entrance": {"left": 666, "top": 569, "right": 706, "bottom": 605, "width": 38, "height": 34}, "explore_is_tales_entrance": {"left": 755, "top": 572, "right": 797, "bottom": 614, "width": 40, "height": 40}, "explore_is_bonus_button": {"left": 349, "top": 7, "right": 439, "bottom": 81, "width": 30, "height": 24}, "explore_is_chapter_entrance_1": {"left": 927, "top": 158, "right": 1118, "bottom": 584, "width": 68, "height": 22}, "explore_is_chapter_entrance_2": {"left": 927, "top": 158, "right": 1118, "bottom": 584, "width": 76, "height": 26}, "explore_is_chapter_entrance_3": {"left": 927, "top": 158, "right": 1118, "bottom": 584, "width": 72, "height": 24}, "explore_is_chapter_entrance_4": {"left": 927, "top": 158, "right": 1118, "bottom": 584, "width": 72, "height": 24}, "explore_is_chapter_entrance_5": {"left": 927, "top": 158, "right": 1118, "bottom": 584, "width": 76, "height": 26}, "explore_is_chapter_entrance_6": {"left": 927, "top": 158, "right": 1118, "bottom": 584, "width": 76, "height": 27}, "explore_is_chapter_entrance_7": {"left": 927, "top": 158, "right": 1118, "bottom": 584, "width": 73, "height": 26}, "explore_is_chapter_entrance_8": {"left": 927, "top": 158, "right": 1118, "bottom": 584, "width": 73, "height": 28}, "explore_is_chapter_entrance_9": {"left": 927, "top": 158, "right": 1118, "bottom": 584, "width": 76, "height": 23}, "explore_is_chapter_entrance_10": {"left": 927, "top": 158, "right": 1118, "bottom": 584, "width": 75, "height": 26}, "explore_is_chapter_entrance_11": {"left": 927, "top": 158, "right": 1118, "bottom": 584, "width": 96, "height": 24}, "explore_is_chapter_entrance_12": {"left": 927, "top": 158, "right": 1118, "bottom": 584, "width": 98, "height": 26}, "explore_is_chapter_entrance_13": {"left": 927, "top": 158, "right": 1118, "bottom": 584, "width": 101, "height": 24}, "explore_is_chapter_entrance_14": {"left": 927, "top": 158, "right": 1118, "bottom": 584, "width": 94, "height": 28}, "explore_is_chapter_entrance_15": {"left": 927, "top": 158, "right": 1118, "bottom": 584, "width": 98, "height": 27}, "explore_is_chapter_entrance_16": {"left": 927, "top": 158, "right": 1118, "bottom": 584, "width": 103, "height": 26}, "explore_is_chapter_entrance_17": {"left": 927, "top": 158, "right": 1118, "bottom": 584, "width": 97, "height": 24}, "explore_is_chapter_entrance_18": {"left": 927, "top": 158, "right": 1118, "bottom": 584, "width": 95, "height": 25}, "explore_is_chapter_entrance_19": {"left": 927, "top": 158, "right": 1118, "bottom": 584, "width": 93, "height": 26}, "explore_is_chapter_entrance_20": {"left": 927, "top": 158, "right": 1118, "bottom": 584, "width": 92, "height": 25}, "explore_is_chapter_entrance_21": {"left": 927, "top": 158, "right": 1118, "bottom": 584, "width": 120, "height": 26}, "explore_is_chapter_entrance_22": {"left": 927, "top": 158, "right": 1118, "bottom": 584, "width": 119, "height": 26}, "explore_is_chapter_entrance_23": {"left": 927, "top": 158, "right": 1118, "bottom": 584, "width": 118, "height": 26}, "explore_is_chapter_entrance_24": {"left": 927, "top": 158, "right": 1118, "bottom": 584, "width": 118, "height": 22}, "explore_is_chapter_entrance_25": {"left": 927, "top": 158, "right": 1118, "bottom": 584, "width": 120, "height": 24}, "explore_is_chapter_entrance_26": {"left": 927, "top": 158, "right": 1118, "bottom": 584, "width": 117, "height": 24}, "explore_is_chapter_entrance_27": {"left": 927, "top": 158, "right": 1118, "bottom": 584, "width": 123, "height": 26}, "explore_is_chapter_entrance_28": {"left": 927, "top": 158, "right": 1118, "bottom": 584, "width": 119, "height": 23}, "explore_is_explore_quit_button": {"left": 25, "top": 32, "right": 74, "bottom": 70, "width": 47, "height": 36}, "explore_is_need_to_set_realm": {"left": 474, "top": 199, "right": 665, "bottom": 226, "width": 189, "height": 25}, "explore_is_kraken_in_explore": {"left": 1, "top": 109, "right": 124, "bottom": 522, "width": 61, "height": 54}, "explore_is_seal_in_explore": {"left": 0, "top": 103, "right": 124, "bottom": 522, "width": 64, "height": 56}, "explore_is_prize_box_in_explore": {"left": 2, "top": 117, "right": 122, "bottom": 535, "width": 55, "height": 46}, "explore_is_seal_panel_in_explore": {"left": 64, "top": 234, "right": 108, "bottom": 414, "width": 42, "height": 178}, "explore_is_seal_panel_in_explore_challenge_button": {"left": 908, "top": 452, "right": 969, "bottom": 508, "width": 59, "height": 54}}